sqlalchemy_informix/__init__.py
sqlalchemy_informix/ibmdb.py
sqlalchemy_informix/requirements.py
sqlalchemy_informix/__pycache__/__init__.cpython-36.pyc
sqlalchemy_informix-0.2.4.dist-info/METADATA
sqlalchemy_informix-0.2.4.dist-info/RECORD
sqlalchemy_informix-0.2.4.dist-info/WHEEL
sqlalchemy_informix-0.2.4.dist-info/entry_points.txt
sqlalchemy_informix-0.2.4.dist-info/top_level.txt
