Metadata-Version: 2.1
Name: sqlalchemy-informix
Version: 0.2.4
Summary: SQLAlchemy informix backend
Home-page: https://gitlab.com/apollo13/sqlalchemy-informix
Author: Florian Apolloner
Author-email: florian@apolloner.eu
License: MIT License
Keywords: SQLAlchemy,Informix
Platform: any
Classifier: Development Status :: 3 - Alpha
Classifier: Environment :: Console
Classifier: Intended Audience :: Developers
Classifier: Programming Language :: Python
Classifier: Programming Language :: Python :: 3
Classifier: Programming Language :: Python :: Implementation :: CPython
Classifier: Topic :: Database :: Front-Ends
Requires-Dist: ibm-db
Requires-Dist: sqlalchemy
